sentry_telegram_py3/__init__.py
sentry_telegram_py3/plugin.py
sentry_telegram_py3-0.6.2.dist-info/LICENSE
sentry_telegram_py3-0.6.2.dist-info/METADATA
sentry_telegram_py3-0.6.2.dist-info/WHEEL
sentry_telegram_py3-0.6.2.dist-info/entry_points.txt
sentry_telegram_py3-0.6.2.dist-info/top_level.txt
sentry_telegram_py3-0.6.2.dist-info/RECORD
